kozmoserver_lightgbm/__init__.py
kozmoserver_lightgbm/lightgbm.py
kozmoserver_lightgbm/version.py
kozmoserver_lightgbm-0.1.0.dev1.dist-info/LICENSE
kozmoserver_lightgbm-0.1.0.dev1.dist-info/METADATA
kozmoserver_lightgbm-0.1.0.dev1.dist-info/WHEEL
kozmoserver_lightgbm-0.1.0.dev1.dist-info/RECORD
